oddsapi/__init__.py
oddsapi/_types.py
oddsapi/aio.py
oddsapi/client.py
oddsapi/exceptions.py
oddsapi-1.2.4.dist-info/LICENSE.txt
oddsapi-1.2.4.dist-info/METADATA
oddsapi-1.2.4.dist-info/WHEEL
oddsapi-1.2.4.dist-info/top_level.txt
oddsapi-1.2.4.dist-info/RECORD
