Metadata-Version: 2.1
Name: oddsapi
Version: 1.2.4
Summary: Python wrapper for The Odds-Api
Home-page: https://github.com/sarartur/oddsapi
Author: Artur Saradzhyan
Author-email: saradzhyanartur@gmail.com
License: UNKNOWN
Platform: UNKNOWN
Classifier: Programming Language :: Python :: 3
Classifier: License :: OSI Approved :: MIT License
Classifier: Operating System :: OS Independent
Requires-Python: >=3.7
Requires-Dist: aiohttp (==3.7.4.post0)
